LICENSE.md
README.md
gapmm2/__init__.py
gapmm2/__main__.py
gapmm2/align.py
gapmm2/utils.py
gapmm2-25.4.13.dist-info/METADATA
gapmm2-25.4.13.dist-info/WHEEL
gapmm2-25.4.13.dist-info/entry_points.txt
gapmm2-25.4.13.dist-info/licenses/LICENSE.md
gapmm2-25.4.13.dist-info/RECORD
