Metadata-Version: 2.4
Name: gapmm2
Version: 25.4.13
Summary: gapmm2: gapped alignment using minimap2
Project-URL: Homepage, https://github.com/nextgenusfs/gapmm2
Project-URL: Repository, https://github.com/nextgenusfs/gapmm2.git
Author-email: Jon Palmer <nextgenusfs@gmail.com>
License: BSD-2-Clause
License-File: LICENSE.md
Classifier: Development Status :: 4 - Beta
Classifier: Intended Audience :: Science/Research
Classifier: License :: OSI Approved :: BSD License
Classifier: Operating System :: Unix
Classifier: Programming Language :: Python
Classifier: Topic :: Scientific/Engineering :: Bio-Informatics
Requires-Python: >=3.6.0
Requires-Dist: edlib
Requires-Dist: mappy
